<toolSet name="External Tools">
  <tool name="Prettier" showInMainMenu="true" showInEditor="true" showInProject="true" showInSearchPopup="true" disabled="false" useConsole="true" showConsoleOnStdOut="false" showConsoleOnStdErr="false" synchronizeAfterRun="true">
    <exec>
      <option name="COMMAND" value="prettier" />
      <option name="PARAMETERS" value="--write --trailing-comma es5 --jsx-bracket-same-line true --print-width 120 $FilePathRelativeToProjectRoot$" />
      <option name="WORKING_DIRECTORY" value="$ProjectFileDir$" />
    </exec>
  </tool>
  <tool name="Prettier Directories" showInMainMenu="true" showInEditor="true" showInProject="true" showInSearchPopup="true" disabled="false" useConsole="true" showConsoleOnStdOut="false" showConsoleOnStdErr="false" synchronizeAfterRun="true">
    <exec>
      <option name="COMMAND" value="prettier" />
      <option name="PARAMETERS" value="--write $FileDirRelativeToProjectRoot$/**/{*.js,*.jsx}" />
      <option name="WORKING_DIRECTORY" value="set $ProjectFileDir$" />
    </exec>
  </tool>
  <tool name="Prettier All JS" description="make all js files of a project Pretty." showInMainMenu="true" showInEditor="true" showInProject="true" showInSearchPopup="true" disabled="false" useConsole="true" showConsoleOnStdOut="false" showConsoleOnStdErr="false" synchronizeAfterRun="true">
    <exec>
      <option name="COMMAND" value="prettier" />
      <option name="PARAMETERS" value="--jsx-bracket-same-line true --print-width 120 --single-quote --trailing-comma es5 --write source/**/*.js" />
      <option name="WORKING_DIRECTORY" value="$ProjectFileDir$" />
    </exec>
  </tool>
  <tool name="HygenComponentFull" description="Generates a new component folder with story, model, provider and e2e tests foundations" showInMainMenu="false" showInEditor="false" showInProject="false" showInSearchPopup="false" disabled="false" useConsole="true" showConsoleOnStdOut="false" showConsoleOnStdErr="false" synchronizeAfterRun="true">
    <exec>
      <option name="COMMAND" value="$ProjectFileDir$/node_modules/.bin/hygen" />
      <option name="PARAMETERS" value="component new --path $FilePathRelativeToProjectRoot$ --name $Prompt$" />
      <option name="WORKING_DIRECTORY" value="$ProjectFileDir$" />
    </exec>
  </tool>
  <tool name="HygenComponentSimple" description="Generates a new functional component folder with story" showInMainMenu="false" showInEditor="false" showInProject="false" showInSearchPopup="false" disabled="false" useConsole="true" showConsoleOnStdOut="false" showConsoleOnStdErr="false" synchronizeAfterRun="true">
    <exec>
      <option name="COMMAND" value="$ProjectFileDir$/node_modules/.bin/hygen" />
      <option name="PARAMETERS" value="component-simple new --path $FilePathRelativeToProjectRoot$ --name $Prompt$" />
      <option name="WORKING_DIRECTORY" value="$ProjectFileDir$" />
    </exec>
  </tool>
  <tool name="HygenProvider" description="Generates a new data provider file" showInMainMenu="false" showInEditor="false" showInProject="false" showInSearchPopup="false" disabled="false" useConsole="true" showConsoleOnStdOut="false" showConsoleOnStdErr="false" synchronizeAfterRun="true">
    <exec>
      <option name="COMMAND" value="$ProjectFileDir$/node_modules/.bin/hygen" />
      <option name="PARAMETERS" value="provider new --path $FilePathRelativeToProjectRoot$ --name $Prompt$" />
      <option name="WORKING_DIRECTORY" value="$ProjectFileDir$" />
    </exec>
  </tool>
</toolSet>